polygongrid/__init__.py
polygongrid/_version.py
polygongrid/main.py
polygongrid-0.1.0.dist-info/LICENSE.txt
polygongrid-0.1.0.dist-info/METADATA
polygongrid-0.1.0.dist-info/WHEEL
polygongrid-0.1.0.dist-info/top_level.txt
polygongrid-0.1.0.dist-info/RECORD
