Metadata-Version: 2.1
Name: polygongrid
Version: 0.1.0
Summary: Generate polygon grids
Home-page: https://github.com/sgoodm/python-polygon-grid
Author: Seth Goodman
Author-email: sgoodman@aiddata.wm.edu
License: BSD
Project-URL: Bug Tracker, https://github.com/sgoodm/python-polygon-grid/issues
Keywords: gis geospatial geographic vector grid
Platform: UNKNOWN
Classifier: Development Status :: 4 - Beta
Classifier: Intended Audience :: Developers
Classifier: Intended Audience :: Science/Research
Classifier: License :: OSI Approved :: BSD License
Classifier: Operating System :: OS Independent
Classifier: Programming Language :: Python :: 3.6
Classifier: Programming Language :: Python :: 3.7
Classifier: Programming Language :: Python :: 3.8
Classifier: Programming Language :: Python :: 3.9
Classifier: Topic :: Utilities
Classifier: Topic :: Scientific/Engineering :: GIS
License-File: LICENSE.txt
Requires-Dist: shapely
